virtual_tweepy/__init__.py
virtual_tweepy/api.py
virtual_tweepy/asynchronous/__init__.py
virtual_tweepy/asynchronous/client.py
virtual_tweepy/asynchronous/pagination.py
virtual_tweepy/asynchronous/streaming.py
virtual_tweepy/auth.py
virtual_tweepy/cache.py
virtual_tweepy/client.py
virtual_tweepy/cursor.py
virtual_tweepy/direct_message_event.py
virtual_tweepy/errors.py
virtual_tweepy/list.py
virtual_tweepy/media.py
virtual_tweepy/mixins.py
virtual_tweepy/models.py
virtual_tweepy/pagination.py
virtual_tweepy/parsers.py
virtual_tweepy/place.py
virtual_tweepy/poll.py
virtual_tweepy/space.py
virtual_tweepy/streaming.py
virtual_tweepy/tweet.py
virtual_tweepy/user.py
virtual_tweepy/utils.py
virtual_tweepy-0.1.1.dist-info/LICENSE
virtual_tweepy-0.1.1.dist-info/METADATA
virtual_tweepy-0.1.1.dist-info/WHEEL
virtual_tweepy-0.1.1.dist-info/RECORD
